msg2bytes/__init__.py
msg2bytes/core.py
msg2bytes/tests.py
msg2bytes-0.1.6.dist-info/licenses/LICENSE
msg2bytes-0.1.6.dist-info/METADATA
msg2bytes-0.1.6.dist-info/WHEEL
msg2bytes-0.1.6.dist-info/top_level.txt
msg2bytes-0.1.6.dist-info/RECORD
