Metadata-Version: 2.4
Name: msg2bytes
Version: 0.1.6
Summary: MessageToBytes(msg2bytes) is an efficient binary serialization format. It lets you exchange data among multiple languages like JSON. But it's faster and smaller.
Author: rRR0VrFP
Maintainer: rRR0VrFP
License: MIT
Keywords: msg2bytes
Classifier: Development Status :: 5 - Production/Stable
Classifier: Intended Audience :: Developers
Classifier: Topic :: Software Development :: Libraries :: Python Modules
Classifier: License :: OSI Approved :: MIT License
Classifier: Programming Language :: Python :: 3
Classifier: Programming Language :: Python :: 3 :: Only
License-File: LICENSE
Requires-Dist: python-dateutil
Dynamic: author
Dynamic: classifier
Dynamic: description
Dynamic: description-content-type
Dynamic: keywords
Dynamic: license
Dynamic: license-file
Dynamic: maintainer
Dynamic: requires-dist
Dynamic: summary
